easyeda2kicad/__init__.py
easyeda2kicad/__main__.py
easyeda2kicad/_version.py
easyeda2kicad/helpers.py
easyeda2kicad/easyeda/__init__.py
easyeda2kicad/easyeda/easyeda_api.py
easyeda2kicad/easyeda/easyeda_importer.py
easyeda2kicad/easyeda/parameters_easyeda.py
easyeda2kicad/easyeda/svg_path_parser.py
easyeda2kicad/kicad/__init__.py
easyeda2kicad/kicad/export_kicad_3d_model.py
easyeda2kicad/kicad/export_kicad_footprint.py
easyeda2kicad/kicad/export_kicad_symbol.py
easyeda2kicad/kicad/parameters_kicad_footprint.py
easyeda2kicad/kicad/parameters_kicad_symbol.py
atopile_easyeda2kicad-0.9.7.dist-info/METADATA
atopile_easyeda2kicad-0.9.7.dist-info/WHEEL
atopile_easyeda2kicad-0.9.7.dist-info/entry_points.txt
atopile_easyeda2kicad-0.9.7.dist-info/licenses/LICENSE
atopile_easyeda2kicad-0.9.7.dist-info/RECORD
