Metadata-Version: 2.4
Name: atopile-easyeda2kicad
Version: 0.9.7
Summary: A Python script that convert any electronic components from LCSC or EasyEDA to a Kicad library
Project-URL: Homepage, https://github.com/uPesy/easyeda2kicad.py
Project-URL: Repository, https://github.com/uPesy/easyeda2kicad.py
Author-email: uPesy <contact@upesy.com>, atopile <info@atopile.io>
License:                     GNU AFFERO GENERAL PUBLIC LICENSE
License-File: LICENSE
Keywords: conversion,easyeda,kicad,library
Classifier: Intended Audience :: Developers
Classifier: License :: OSI Approved :: GNU Affero General Public License v3
Classifier: Natural Language :: English
Classifier: Programming Language :: Python :: 3
Classifier: Programming Language :: Python :: 3.12
Classifier: Programming Language :: Python :: 3.13
Classifier: Topic :: Scientific/Engineering :: Electronic Design Automation (EDA)
Requires-Python: >=3.12
Requires-Dist: httpx>=0.28.1
Requires-Dist: pydantic>=2.5.0
Requires-Dist: truststore>=0.10.4
Provides-Extra: dev
Requires-Dist: mypy>=1.14.1; extra == 'dev'
Requires-Dist: pre-commit>=3.6.0; extra == 'dev'
Requires-Dist: ruff>=0.8.4; extra == 'dev'
